couchbase_sqlalchemy/__init__.py
couchbase_sqlalchemy/dbapi/__init__.py
couchbase_sqlalchemy/dbapi/couchbase_dbapi.py
couchbase_sqlalchemy/dialect/__init__.py
couchbase_sqlalchemy/dialect/couchbase_dialect.py
couchbase_sqlalchemy-1.0.1.dist-info/LICENSE
couchbase_sqlalchemy-1.0.1.dist-info/METADATA
couchbase_sqlalchemy-1.0.1.dist-info/WHEEL
couchbase_sqlalchemy-1.0.1.dist-info/entry_points.txt
couchbase_sqlalchemy-1.0.1.dist-info/top_level.txt
couchbase_sqlalchemy-1.0.1.dist-info/RECORD
