Metadata-Version: 2.1
Name: couchbase-sqlalchemy
Version: 1.0.1
Summary: A SQLAlchemy dialect for Couchbase Analytics/Columnar.
Author: Ayush Tripathi
Author-email: ayush.tripathi@couchbase.com
License: Apache-2.0
Keywords: Couchbase db database cloud analytics Columnar
License-File: LICENSE
Requires-Dist: sqlalchemy <2.0,>=1.3.0
Requires-Dist: couchbase >=4.0.0
